MANIFEST.in
README.md
exception_slacker.py
requirements.txt
setup.py
exception_slacker.egg-info/PKG-INFO
exception_slacker.egg-info/SOURCES.txt
exception_slacker.egg-info/dependency_links.txt
exception_slacker.egg-info/not-zip-safe
exception_slacker.egg-info/requires.txt
exception_slacker.egg-info/top_level.txt