Metadata-Version: 1.0
Name: exception-slacker
Version: 0.1.1
Summary: Notify exceptions on slack
Home-page: https://github.com/hassaku/exception_slacker
Author: hassaku
Author-email: hassaku.apps@gmail.com
License: MIT
Keywords: slack exception
Platform: UNKNOWN
